pulumi_containerregistry/__init__.py
pulumi_containerregistry/_utilities.py
pulumi_containerregistry/provider.py
pulumi_containerregistry/pulumi-plugin.json
pulumi_containerregistry/py.typed
pulumi_containerregistry/resource.py
pulumi_containerregistry-0.0.17.dist-info/METADATA
pulumi_containerregistry-0.0.17.dist-info/WHEEL
pulumi_containerregistry-0.0.17.dist-info/top_level.txt
pulumi_containerregistry-0.0.17.dist-info/RECORD
